DISB.py
disb-2.1.0.2.dist-info/METADATA
disb-2.1.0.2.dist-info/WHEEL
disb-2.1.0.2.dist-info/licenses/LICENSE
disb-2.1.0.2.dist-info/RECORD
