Metadata-Version: 2.4
Name: DISB
Version: 2.1.0.2
Summary: this is the "discord infinity storage bot", it basically turns discord into unlimited cloud storage
Project-URL: Homepage, https://github.com/WeDu-official/DISB
Project-URL: Issues, https://github.com/WeDu-official/DISB/issues
Author-email: WeDu-official <fplu.the.founder@gmail.com>
License-File: LICENSE
Classifier: Development Status :: 6 - Mature
Classifier: Intended Audience :: Developers
Classifier: License :: Other/Proprietary License
Classifier: Natural Language :: English
Classifier: Operating System :: Microsoft :: Windows :: Windows 8.1
Classifier: Operating System :: Microsoft :: Windows :: Windows 10
Classifier: Operating System :: Microsoft :: Windows :: Windows 11
Classifier: Programming Language :: Python :: 3.8
Classifier: Programming Language :: Python :: 3.9
Classifier: Programming Language :: Python :: 3.10
Classifier: Programming Language :: Python :: 3.11
Classifier: Programming Language :: Python :: 3.12
Classifier: Programming Language :: Python :: 3.13
Classifier: Topic :: Home Automation
Classifier: Topic :: Multimedia :: Graphics :: Capture :: Digital Camera
Classifier: Topic :: Multimedia :: Video :: Capture
Classifier: Topic :: Scientific/Engineering :: Image Processing
Classifier: Topic :: Scientific/Engineering :: Image Recognition
Requires-Python: >=3.10
Requires-Dist: aiohttp>=3.11.18
Requires-Dist: discord-py>=2.5.2
Requires-Dist: powerdb>=2.2.5.3
